Metadata-Version: 2.1
Name: aiohttp_remotes
Version: 1.2.0
Summary: Control remote side information.
Home-page: https://github.com/aio-libs/aiohttp-remotes
Author: Andrew Svetlov
Author-email: andrew.svetlov@gmail.com
Requires-Python: >=3.6
Classifier: License :: OSI Approved :: MIT License
Classifier: Programming Language :: Python :: 3
Classifier: Programming Language :: Python :: 3.7
Classifier: Programming Language :: Python :: 3.8
Classifier: Programming Language :: Python :: 3.9
Classifier: Programming Language :: Python :: 3.10
Classifier: Topic :: Software Development :: Libraries :: Python Modules
Classifier: Development Status :: 5 - Production/Stable
Classifier: Framework :: AsyncIO
Requires-Dist: aiohttp >= 3.8.1
Requires-Dist: typing-extensions >= 3.7.4
Project-URL: Documentation, https://aiohttp-remotes.readthedocs.io
